hanzo_tools/__init__.py
hanzo_tools/browser/__init__.py
hanzo_tools/browser/browser_tool.py
hanzo_tools/browser/cdp_bridge_server.py
hanzo_tools_browser-0.2.2.dist-info/METADATA
hanzo_tools_browser-0.2.2.dist-info/WHEEL
hanzo_tools_browser-0.2.2.dist-info/entry_points.txt
hanzo_tools_browser-0.2.2.dist-info/top_level.txt
hanzo_tools_browser-0.2.2.dist-info/RECORD
