Metadata-Version: 2.4
Name: hanzo-tools-browser
Version: 0.2.2
Summary: Browser automation tools with extension-first routing - uses Hanzo browser extension when available, Playwright as fallback
Author-email: Hanzo Industries Inc <dev@hanzo.ai>
License: MIT
Keywords: hanzo,tools,browser,playwright,mcp,ai,automation,extension
Requires-Python: >=3.12
Requires-Dist: hanzo-tools>=0.3.0
Requires-Dist: mcp>=1.25.0
Requires-Dist: pydantic>=2.12.5
Requires-Dist: aiohttp>=3.9.0
Provides-Extra: playwright
Requires-Dist: playwright>=1.49.0; extra == "playwright"
